is_it_stream.py
osustreams-1.1.1.dist-info/entry_points.txt
osustreams-1.1.1.dist-info/LICENSE
osustreams-1.1.1.dist-info/WHEEL
osustreams-1.1.1.dist-info/METADATA
osustreams-1.1.1.dist-info/RECORD
