Metadata-Version: 2.1
Name: osustreams
Version: 1.1.1
Summary: find stream maps in your osu library
Home-page: https://github.com/upgradeQ/OSU-STREAM-DETECTOR
License: MPL-2.0
Keywords: osu,stream,export,beatmap,search
Author: upgradeq
Author-email: noreply@example.com
Requires-Python: >=3.6,<4.0
Classifier: Intended Audience :: End Users/Desktop
Classifier: License :: OSI Approved
Classifier: Natural Language :: English
Classifier: Operating System :: OS Independent
Classifier: Programming Language :: Python :: 3
Classifier: Programming Language :: Python :: 3 :: Only
Classifier: Programming Language :: Python :: 3.6
Classifier: Programming Language :: Python :: 3.7
Classifier: Programming Language :: Python :: 3.8
Classifier: Topic :: Utilities
Project-URL: Documentation, https://github.com/upgradeQ/OSU-STREAM-DETECTOR/blob/master/README.md
Project-URL: Repository, https://github.com/upgradeQ/OSU-STREAM-DETECTOR
